geoml_kit/__init__.py
geoml_kit/common.py
geoml_kit/geoml_kit.py
geoml_kit-0.0.3.dist-info/licenses/LICENSE
geoml_kit-0.0.3.dist-info/METADATA
geoml_kit-0.0.3.dist-info/WHEEL
geoml_kit-0.0.3.dist-info/entry_points.txt
geoml_kit-0.0.3.dist-info/top_level.txt
geoml_kit-0.0.3.dist-info/RECORD
